pyliblo3/_liblo.cp312-win_amd64.pyd
pyliblo3/_liblo.pyi
pyliblo3/__init__.py
pyliblo3-0.16.3.data/scripts/dump_osc.py
pyliblo3-0.16.3.data/scripts/send_osc.py
pyliblo3-0.16.3.dist-info/COPYING
pyliblo3-0.16.3.dist-info/DELVEWHEEL
pyliblo3-0.16.3.dist-info/METADATA
pyliblo3-0.16.3.dist-info/RECORD
pyliblo3-0.16.3.dist-info/top_level.txt
pyliblo3-0.16.3.dist-info/WHEEL
pyliblo3.libs/liblo-9e4ac2afd4c3b992a79ee81654959ba6.dll
