Metadata-Version: 2.1
Name: pyliblo3
Version: 0.16.3
Summary: Python bindings for the liblo OSC library
Home-page: https://github.com/gesellkammer/pyliblo3
Author: Dominic Sacre
Author-email: dominic.sacre@gmx.de
Maintainer: Eduardo Moguillansky
Maintainer-email: eduardo.moguillansky@gmail.com
License: LGPL
Requires-Python: >=3.9
License-File: COPYING
